{
  "Users": [
    {
      "id": 1,
      "name": "pawan balla",
      "email": "baluangular225@gmail.com",
      "website": "Capgemini"
    },
    {
      "id": 2,
      "name": "pawan kumar",
      "email": "pavankumar225@gmail.com",
      "website": "Infosys"
    },
    {
      "id": "d2f1",
      "name": "React My Life",
      "email": "baluangular225@gmail.com",
      "website": "anastasia.net"
    },
    {
      "id": "d3bb",
      "name": "Hello React",
      "email": "react.123@gmail.com",
      "website": "anastasia.net"
    },
    {
      "id": "8adb",
      "name": "Balu React",
      "email": "balunaidu@gmail.com",
      "website": "react.org"
    },
    {
      "id": "6091",
      "name": "React My Life",
      "email": "baluangular225@gmail.com",
      "website": "react"
    },
    {
      "id": "e494",
      "name": "React My Life",
      "email": "Sincere@april.biz",
      "website": "ramiro.info"
    },
    {
      "id": "e0d6",
      "name": "React My Life",
      "email": "baluangular225@gmail.com",
      "website": "Capgemin.com"
    },
    {
      "id": "b022",
      "alldata": {
        "name": "React My Life",
        "email": "baluangular225@gmail.com",
        "website": "Capgemini.com"
      }
    },
    {
      "id": "0f8e",
      "alldata": {
        "name": "New React",
        "email": "Shanna@melissa.tv",
        "website": "ramiro.info"
      }
    },
    {
      "id": "c3ba",
      "alldata": {
        "name": "New Course",
        "email": "baluangular225@gmail.com",
        "website": "hildegard.org"
      }
    },
    {
      "id": "7813",
      "alldata": {
        "name": "React My Life",
        "email": "baluangular225@gmail.com",
        "website": "react.org"
      }
    },
    {
      "id": "8c77",
      "name": "React My Life",
      "email": "baluangular225@gmail.com",
      "website": "Capgemini.com"
    },
    {
      "id": "229d",
      "userDetails": {
        "name": "React My Life",
        "email": "baluangular225@gmail.com",
        "website": "react.org"
      }
    },
    {
      "id": "c54c",
      "userDetails": {
        "name": "React World Wide",
        "email": "balunew225@gmail.com",
        "website": "balunaidu.org"
      }
    },
    {
      "id": "b8e7",
      "userDetails": {
        "name": "This is My New Data",
        "email": "mynewdata225@gmail.com",
        "website": "mydata.org"
      }
    },
    {
      "id": "7d87",
      "name": "This is Update Data",
      "email": "updatedata225@gmail.com",
      "website": "updatedata.org"
    },
    {
      "id": "98a6",
      "name": "React My Life",
      "email": "baluangular225@gmail.com",
      "website": "react.org"
    },
    {
      "id": "bb1b",
      "name": "React My Life",
      "email": "baluangular225@gmail.co",
      "website": "react.org"
    },
    {
      "id": "f7eb",
      "name": "React My Life",
      "email": "react.123@gmail.com",
      "website": "hildegard.org"
    },
    {
      "id": "5d28",
      "name": "React My Life",
      "email": "baluangular225@gmail.com",
      "website": "Usepost3"
    },
    {
      "id": "58cb",
      "name": "React is Powerfull Language",
      "email": "reactpowerful123@gail.com",
      "website": "react.in"
    },
    {
      "id": "6a00",
      "name": "React My Life",
      "email": "baluangular225@gmail.com",
      "website": "react.org"
    },
    {
      "id": 15,
      "name": "balla",
      "email": "baluangular225@gmail.com",
      "website": "Capgemini.com"
    },
    {
      "id": "ce12",
      "name": "React Update All Times",
      "email": "reactupdate123@gmail.com",
      "website": "react.in"
    },
    {
      "id": "4b4a",
      "name": "React My Life",
      "email": "baluangular225@gmail.com",
      "website": "react.co.in"
    },
    {
      "id": "398a",
      "name": "React World",
      "email": "baluangular225@gmail.com",
      "website": "react.arm"
    },
    {
      "id": "df40",
      "name": "React World",
      "email": "react.123@gmail.com",
      "website": "react.arm"
    },
    {
      "id": "d081",
      "name": "My New Data",
      "email": "mynewdata@gmail.com",
      "website": "mynewdata.org"
    },
    {
      "id": "4451",
      "name": "React My World",
      "email": "Sincere@april.biz",
      "website": "react.org"
    },
    {
      "id": "f9b0",
      "name": "Arrays Methods",
      "email": "arraymethods@gmail.com",
      "website": "arraymethod.org"
    },
    {
      "id": "3a88",
      "name": "React My Life",
      "email": "baluangular225@gmail.com",
      "website": "capgemini.org"
    },
    {
      "id": "78ae",
      "name": "React123",
      "email": "react123@gmail.com",
      "website": "react123.org"
    },
    {
      "id": "7344",
      "name": "Today Pratice",
      "email": "todaypratice@gmail.com",
      "website": "todaypratice.org"
    },
    {
      "id": "5fc3",
      "name": "Hello",
      "email": "baluangular225@gmail.com",
      "website": "Capgemini.com"
    },
    {
      "id": "55a1",
      "name": "New Project",
      "email": "newproject123@capgemini.com",
      "website": "newproject.org"
    },
    {
      "id": "c414",
      "name": "Balu React",
      "email": "baluangular225@gmail.com",
      "website": "balu.org"
    },
    {
      "id": "c71d",
      "name": "Naukuri",
      "email": "naukuri123@gmail.com",
      "website": "naukuri.org"
    },
    {
      "id": "9920",
      "name": "React 123",
      "email": "Shanna@melissa.tv",
      "website": "Capgemini.com"
    },
    {
      "id": "9847",
      "name": "Hello",
      "email": "react.123@gmail.com",
      "website": "hello.org"
    },
    {
      "id": "ff12",
      "name": "React My Life",
      "email": "baluangular225@gmail.com",
      "website": "today.org"
    }
  ],
  "Employes": [
    {
      "id": 1,
      "name": "Venu",
      "email": "venugopal@gmail.com"
    },
    {
      "id": 2,
      "name": "bala swami",
      "email": "bala@gmail.com"
    }
  ],
  "Admin": [
    {
      "id": 1,
      "name": "pavan",
      "email": "pavan@gmail.com"
    },
    {
      "id": 1,
      "name": "swami",
      "email": "bala@gmail.com"
    }
  ]
}